penisipsum/__init__.py
penisipsum-2020.7.2.dist-info/LICENSE
penisipsum-2020.7.2.dist-info/METADATA
penisipsum-2020.7.2.dist-info/WHEEL
penisipsum-2020.7.2.dist-info/top_level.txt
penisipsum-2020.7.2.dist-info/RECORD
