Metadata-Version: 2.1
Name: penisipsum
Version: 2020.7.2
Summary: penis ipsum
Home-page: https://github.com/jordiprats/python-penisipsum
Author: Jordi Prats
Author-email: jprats@systemadmin.es
License: UNKNOWN
Platform: UNKNOWN
Classifier: Operating System :: OS Independent
